zapit_python_bridge/__init__.py
zapit_python_bridge/bridge.py
zapit_Python_Bridge-0.1.3.dist-info/LICENSE
zapit_Python_Bridge-0.1.3.dist-info/METADATA
zapit_Python_Bridge-0.1.3.dist-info/WHEEL
zapit_Python_Bridge-0.1.3.dist-info/top_level.txt
zapit_Python_Bridge-0.1.3.dist-info/RECORD
